clicast/__init__.py
clicast/cast.py
clicast/editor.py
clicast/filters.py
clicast-1.0.1.dist-info/LICENSE
clicast-1.0.1.dist-info/METADATA
clicast-1.0.1.dist-info/WHEEL
clicast-1.0.1.dist-info/entry_points.txt
clicast-1.0.1.dist-info/top_level.txt
clicast-1.0.1.dist-info/RECORD
