Metadata-Version: 2.1
Name: clicast
Version: 1.0.1
Summary: Broadcast messages for CLI tools, such as a warning for critical bug or notification about new features.
Home-page: https://github.com/maxzheng/clicast
Author: Max Zheng
Author-email: maxzheng.os @t gmail.com
License: MIT
Keywords: cli broadcast command warning critical bug
Classifier: Development Status :: 5 - Production/Stable
Classifier: Intended Audience :: Developers
Classifier: Topic :: Software Development
Classifier: License :: OSI Approved :: MIT License
Classifier: Programming Language :: Python :: 3
License-File: LICENSE
Requires-Dist: localconfig ==1.1.*
Requires-Dist: remoteconfig
Requires-Dist: requests
